{
  "CustomVehicles": [
    {
      "DashboardColorIndex": 61,
      "EnvEffScale": -1.000000,
      "Flags": {
        "BulletproofTyres": true,
        "CustomPrimaryColor": false,
        "CustomSecondaryColor": false,
        "ExtraFlag1": false,
        "ExtraFlag10": false,
        "ExtraFlag11": false,
        "ExtraFlag12": false,
        "ExtraFlag2": false,
        "ExtraFlag3": false,
        "ExtraFlag4": false,
        "ExtraFlag5": false,
        "ExtraFlag6": false,
        "ExtraFlag7": false,
        "ExtraFlag8": false,
        "ExtraFlag9": false,
        "NeonBack": true,
        "NeonFront": true,
        "NeonLeft": true,
        "NeonRight": true
      },
      "InteriorColorIndex": 132,
      "ModelHash": 1909189272,
      "Name": "Unknown [GB200 (maxed)]",
      "NeonColor": {
        "b": 255,
        "g": 255,
        "r": 255
      },
      "NumberPlateIndex": 1,
      "NumberPlateText": "WH100",
      "PearlesentColorIndex": 158,
      "PrimaryColor": {
        "b": 5,
        "g": 5,
        "r": 5
      },
      "PrimaryColorIndex": 158,
      "SecondaryColor": {
        "b": 57,
        "g": 90,
        "r": 131
      },
      "SecondaryColorIndex": 158,
      "TyreSmokeColor": {
        "b": 3,
        "g": 3,
        "r": 133
      },
      "VehicleMods": [
        3,
        4,
        3,
        1,
        1,
        5,
        3,
        10,
        1,
        -1,
        1,
        4,
        3,
        3,
        58,
        5,
        5,
        1,
        1,
        1,
        1,
        1,
        1,
        217,
        -1,
        -1,
        -1,
        -1,
        -1,
        -1,
        -1,
        -1,
        -1,
        -1,
        -1,
        -1,
        -1,
        -1,
        -1,
        -1,
        -1,
        -1,
        -1,
        -1,
        -1,
        -1,
        -1,
        -1,
        10
      ],
      "WheelColorIndex": 156,
      "WheelType": 9,
      "WheelVariations": [
        1,
        1
      ],
      "WindowTint": 1
    },
    {
      "DashboardColorIndex": 61,
      "EnvEffScale": -1.000000,
      "Flags": {
        "BulletproofTyres": true,
        "CustomPrimaryColor": false,
        "CustomSecondaryColor": false,
        "ExtraFlag1": false,
        "ExtraFlag10": false,
        "ExtraFlag11": false,
        "ExtraFlag12": false,
        "ExtraFlag2": false,
        "ExtraFlag3": false,
        "ExtraFlag4": false,
        "ExtraFlag5": false,
        "ExtraFlag6": false,
        "ExtraFlag7": false,
        "ExtraFlag8": false,
        "ExtraFlag9": false,
        "NeonBack": true,
        "NeonFront": true,
        "NeonLeft": true,
        "NeonRight": true
      },
      "InteriorColorIndex": 132,
      "ModelHash": 1909189272,
      "Name": "Unknown [GB200 (maxed)]",
      "NeonColor": {
        "b": 255,
        "g": 255,
        "r": 255
      },
      "NumberPlateIndex": 1,
      "NumberPlateText": "WH100",
      "PearlesentColorIndex": 158,
      "PrimaryColor": {
        "b": 5,
        "g": 5,
        "r": 5
      },
      "PrimaryColorIndex": 158,
      "SecondaryColor": {
        "b": 57,
        "g": 90,
        "r": 131
      },
      "SecondaryColorIndex": 158,
      "TyreSmokeColor": {
        "b": 3,
        "g": 3,
        "r": 133
      },
      "VehicleMods": [
        3,
        4,
        3,
        1,
        1,
        5,
        3,
        10,
        1,
        -1,
        1,
        4,
        3,
        3,
        58,
        5,
        5,
        1,
        1,
        1,
        1,
        1,
        1,
        217,
        -1,
        -1,
        -1,
        -1,
        -1,
        -1,
        -1,
        -1,
        -1,
        -1,
        -1,
        -1,
        -1,
        -1,
        -1,
        -1,
        -1,
        -1,
        -1,
        -1,
        -1,
        -1,
        -1,
        -1,
        10
      ],
      "WheelColorIndex": 156,
      "WheelType": 9,
      "WheelVariations": [
        1,
        1
      ],
      "WindowTint": 1
    }
  ]
}